importutils/__init__.py
importutils/importutils.py
importutils-0.1.dist-info/METADATA
importutils-0.1.dist-info/WHEEL
importutils-0.1.dist-info/top_level.txt
importutils-0.1.dist-info/RECORD
