Metadata-Version: 2.1
Name: importutils
Version: 0.1
Summary: Utility to import the minimal dependencies during computer vision project
Home-page: https://github.com/dattran2346/importutils
Author: Tran Quang Dat
Author-email: dattran2346@gmail.com
License: MIT
Platform: UNKNOWN
